programs/run_ttsim3d.py
ttsim3d/__init__.py
ttsim3d/device_handler.py
ttsim3d/elastic_scattering_factors.json
ttsim3d/grid_coords.py
ttsim3d/models.py
ttsim3d/mrc_handler.py
ttsim3d/pdb_handler.py
ttsim3d/scattering_potential.py
ttsim3d/simulate3d.py
ttsim3d/data/README.md
ttsim3d/data/mtf_de20_300kV.star
ttsim3d/data/mtf_falcon2_300kV.star
ttsim3d/data/mtf_falcon3EC_200kV.star
ttsim3d/data/mtf_falcon3EC_300kV.star
ttsim3d/data/mtf_falcon4EC_200kV.star
ttsim3d/data/mtf_falcon4EC_300kV.star
ttsim3d/data/mtf_k2_200kV_FL2.star
ttsim3d/data/mtf_k2_300kV.star
ttsim3d/data/mtf_k2_300kV_FL2.star
ttsim3d/data/mtf_k3_standard_200kV_FL2.star
ttsim3d/data/mtf_k3_standard_300kV_FL2.star
ttsim3d-0.4.0.dist-info/METADATA
ttsim3d-0.4.0.dist-info/WHEEL
ttsim3d-0.4.0.dist-info/entry_points.txt
ttsim3d-0.4.0.dist-info/licenses/LICENSE
ttsim3d-0.4.0.dist-info/RECORD
