Metadata-Version: 2.4
Name: ttsim3d
Version: 0.4.0
Summary: Simulate a 3D electrostatic potential map from a PDB in pyTorch
Project-URL: homepage, https://github.com/jdickerson95/ttsim3d
Project-URL: repository, https://github.com/jdickerson95/ttsim3d
Author-email: Josh Dickerson <jdickerson@berkeley.edu>
License: BSD-3-Clause
License-File: LICENSE
Classifier: Development Status :: 3 - Alpha
Classifier: License :: OSI Approved :: BSD License
Classifier: Programming Language :: Python :: 3
Classifier: Programming Language :: Python :: 3.10
Classifier: Programming Language :: Python :: 3.11
Classifier: Programming Language :: Python :: 3.12
Classifier: Typing :: Typed
Requires-Python: >=3.9
Requires-Dist: click
Requires-Dist: einops
Requires-Dist: mmdf
Requires-Dist: mrcfile
Requires-Dist: psutil
Requires-Dist: pydantic
Requires-Dist: requests
Requires-Dist: scipy
Requires-Dist: starfile
Requires-Dist: torch
Requires-Dist: torch-fourier-filter>=0.2.4
Requires-Dist: torch-grid-utils
Provides-Extra: dev
Requires-Dist: ipython; extra == 'dev'
Requires-Dist: mypy; extra == 'dev'
Requires-Dist: pdbpp; extra == 'dev'
Requires-Dist: pre-commit; extra == 'dev'
Requires-Dist: rich; extra == 'dev'
Requires-Dist: ruff; extra == 'dev'
Provides-Extra: test
Requires-Dist: pytest; extra == 'test'
Requires-Dist: pytest-cov; extra == 'test'
Requires-Dist: requests; extra == 'test'
